pyanalysis/__init__.py
pyanalysis/client.py
pyanalysis/asyncio/__init__.py
pyanalysis/asyncio/client.py
tests/general-async.py
tests/general.py
pyanalysis-2.4.5.dist-info/METADATA
pyanalysis-2.4.5.dist-info/WHEEL
pyanalysis-2.4.5.dist-info/top_level.txt
pyanalysis-2.4.5.dist-info/RECORD
