Metadata-Version: 2.2
Name: pyanalysis
Version: 2.4.5
Summary: Python Library for pyanalysis.ptsecurity.tech
Author-email: Stanislav Rakovsky <iam@disasm.me>
License: MIT
Classifier: Development Status :: 3 - Alpha
Classifier: License :: OSI Approved :: MIT License
Classifier: Programming Language :: Python :: 3
Requires-Python: >=3.6
Requires-Dist: requests>=2.32.0
Requires-Dist: aiohttp>=3.8.1
Requires-Dist: logzero>=1.7.0
